Metadata-Version: 1.1
Name: sub-finder
Version: 0.0.1
Summary: Module to get all subsidiaries of the given company
Home-page: UNKNOWN
Author: Aswin venkat
Author-email: aswin.venkat@cybersecurityworks.com
License: MIT
Keywords: subsidiaries,edgar
Platform: UNKNOWN
Classifier: Development Status :: 5 - Production/Stable
Classifier: Intended Audience :: Education
Classifier: Operating System :: Microsoft :: Windows :: Windows 10
Classifier: License :: OSI Approved :: MIT License
Classifier: Programming Language :: Python :: 3
